Workbook

Sheet Start Here
B2: CONTRACTOR JOB PACK
B3: Quote · Invoice · Change Order · Mileage Log · Price Book — all in one file
B5: YOUR COMPANY DETAILS — fill in once, it appears on every document
B6: Company Name | C6: Your Company Name
B7: Address Line | C7: 123 Main Street
B8: City, State, ZIP | C8: Anytown, ST 00000
B9: Phone | C9: (555) 555-5555
B10: Email | C10: you@yourcompany.com
B11: Website | C11: www.yourcompany.com
B13: To add a logo: Insert > Image, then position it near the top of this sheet.
B15: HOW THIS FILE WORKS
B16: Tabs: | C16: Each tab at the bottom is one document: Quote, Invoice, Change Order, Mileage Log. Price Book holds your services/products.
B17: Gray cells: | C17: Anything shaded light gray is meant to be edited — company info, client info, line items, quantities, rates.
B18: Price Book: | C18: Add every service or product you sell as a row on the Price Book tab. It then appears as a dropdown on the Quote and Invoice tabs.
B19: Quote to Invoice: | C19: Invoice automatically mirrors the Quote's line items and pulls in any Change Order cost impacts as extra charges. Need to bill something differently than quoted? Type over that one cell on Invoice — it just stops linking for that cell, nothing else breaks.
B20: One file per job: | C20: This linking assumes one job = one copy of this file. A second Change Order or a second partial invoice for the same job means duplicating that tab (right-click the tab > Move or Copy) rather than something this file tracks automatically.
B21: Printing / PDF: | C21: Click the tab you want, then File > Print (or Export > PDF). Each tab is already sized to print on one page.
B22: Re-styling: | C22: Header bars and shaded fields use Cell Styles (Home tab > Cell Styles). Right-click a style there to change the color everywhere it's used, across every tab, in one edit.

Sheet Price Book
A1: PRICE BOOK
A2: Add, edit, or remove rows below. The Item dropdown on Quote and Invoice updates automatically.
A4: Item Code / Name | B4: Description | C4: Unit Price | D4: Category
A5: Consulting - Hourly | B5: General consulting services, billed hourly | C5: 85 | D5: Services
A6: Design - Hourly | B6: Design work, billed hourly | C6: 75 | D6: Services
A7: Standard Callout | B7: Standard job / site visit fee | C7: 60 | D7: Fee
A8: Rush Fee | B8: Expedited turnaround surcharge | C8: 50 | D8: Fee

Sheet Quote
B2: =CompanyName -> Your Company Name | E2: QUOTE
B3: =CompanyAddress&", "&CompanyCityStateZip -> 123 Main Street, Anytown, ST 00000
B4: =CompanyPhone&" · "&CompanyEmail -> (555) 555-5555 · you@yourcompany.com | E4: Quote # | F4: QUO-0001
E5: Date | F5: =TODAY() -> 46276
E6: Valid Until | F6: =F5+30 -> 46306
B8: PREPARED FOR
B9: Client / Company Name
B13: Item | C13: Description | D13: Qty | E13: Unit Price | F13: Line Total
C14: =IF(B14="","",IFERROR(INDEX('Price Book'!$B$5:$B$45,MATCH(B14,'Price Book'!$A$5:$A$45,0)),"")) | E14: =IF(B14="","",IFERROR(INDEX('Price Book'!$C$5:$C$45,MATCH(B14,'Price Book'!$A$5:$A$45,0)),"")) | F14: =IF(OR(B14="",D14=""),"",D14*E14)
C15: =IF(B15="","",IFERROR(INDEX('Price Book'!$B$5:$B$45,MATCH(B15,'Price Book'!$A$5:$A$45,0)),"")) | E15: =IF(B15="","",IFERROR(INDEX('Price Book'!$C$5:$C$45,MATCH(B15,'Price Book'!$A$5:$A$45,0)),"")) | F15: =IF(OR(B15="",D15=""),"",D15*E15)
C16: =IF(B16="","",IFERROR(INDEX('Price Book'!$B$5:$B$45,MATCH(B16,'Price Book'!$A$5:$A$45,0)),"")) | E16: =IF(B16="","",IFERROR(INDEX('Price Book'!$C$5:$C$45,MATCH(B16,'Price Book'!$A$5:$A$45,0)),"")) | F16: =IF(OR(B16="",D16=""),"",D16*E16)
C17: =IF(B17="","",IFERROR(INDEX('Price Book'!$B$5:$B$45,MATCH(B17,'Price Book'!$A$5:$A$45,0)),"")) | E17: =IF(B17="","",IFERROR(INDEX('Price Book'!$C$5:$C$45,MATCH(B17,'Price Book'!$A$5:$A$45,0)),"")) | F17: =IF(OR(B17="",D17=""),"",D17*E17)
C18: =IF(B18="","",IFERROR(INDEX('Price Book'!$B$5:$B$45,MATCH(B18,'Price Book'!$A$5:$A$45,0)),"")) | E18: =IF(B18="","",IFERROR(INDEX('Price Book'!$C$5:$C$45,MATCH(B18,'Price Book'!$A$5:$A$45,0)),"")) | F18: =IF(OR(B18="",D18=""),"",D18*E18)
C19: =IF(B19="","",IFERROR(INDEX('Price Book'!$B$5:$B$45,MATCH(B19,'Price Book'!$A$5:$A$45,0)),"")) | E19: =IF(B19="","",IFERROR(INDEX('Price Book'!$C$5:$C$45,MATCH(B19,'Price Book'!$A$5:$A$45,0)),"")) | F19: =IF(OR(B19="",D19=""),"",D19*E19)
C20: =IF(B20="","",IFERROR(INDEX('Price Book'!$B$5:$B$45,MATCH(B20,'Price Book'!$A$5:$A$45,0)),"")) | E20: =IF(B20="","",IFERROR(INDEX('Price Book'!$C$5:$C$45,MATCH(B20,'Price Book'!$A$5:$A$45,0)),"")) | F20: =IF(OR(B20="",D20=""),"",D20*E20)
C21: =IF(B21="","",IFERROR(INDEX('Price Book'!$B$5:$B$45,MATCH(B21,'Price Book'!$A$5:$A$45,0)),"")) | E21: =IF(B21="","",IFERROR(INDEX('Price Book'!$C$5:$C$45,MATCH(B21,'Price Book'!$A$5:$A$45,0)),"")) | F21: =IF(OR(B21="",D21=""),"",D21*E21)
C22: =IF(B22="","",IFERROR(INDEX('Price Book'!$B$5:$B$45,MATCH(B22,'Price Book'!$A$5:$A$45,0)),"")) | E22: =IF(B22="","",IFERROR(INDEX('Price Book'!$C$5:$C$45,MATCH(B22,'Price Book'!$A$5:$A$45,0)),"")) | F22: =IF(OR(B22="",D22=""),"",D22*E22)
C23: =IF(B23="","",IFERROR(INDEX('Price Book'!$B$5:$B$45,MATCH(B23,'Price Book'!$A$5:$A$45,0)),"")) | E23: =IF(B23="","",IFERROR(INDEX('Price Book'!$C$5:$C$45,MATCH(B23,'Price Book'!$A$5:$A$45,0)),"")) | F23: =IF(OR(B23="",D23=""),"",D23*E23)
C24: =IF(B24="","",IFERROR(INDEX('Price Book'!$B$5:$B$45,MATCH(B24,'Price Book'!$A$5:$A$45,0)),"")) | E24: =IF(B24="","",IFERROR(INDEX('Price Book'!$C$5:$C$45,MATCH(B24,'Price Book'!$A$5:$A$45,0)),"")) | F24: =IF(OR(B24="",D24=""),"",D24*E24)
C25: =IF(B25="","",IFERROR(INDEX('Price Book'!$B$5:$B$45,MATCH(B25,'Price Book'!$A$5:$A$45,0)),"")) | E25: =IF(B25="","",IFERROR(INDEX('Price Book'!$C$5:$C$45,MATCH(B25,'Price Book'!$A$5:$A$45,0)),"")) | F25: =IF(OR(B25="",D25=""),"",D25*E25)
... C27: =IF(B27="","",IFERROR(INDEX('Price Book'!$B$5:$B$45,MATCH(B27,'Price Book'!$A$5:$A$45,0)),"")) | E27: =IF(B27="","",IFERROR(INDEX('Price Book'!$C$5:$C$45,MATCH(B27,'Price Book'!$A$5:$A$45,0)),"")) | F27: =IF(OR(B27="",D27=""),"",D27*E27)
D29: Subtotal | F29: =SUM(F14:F27) -> 0
D30: Tax | E30: 0 | F30: =F29*E30 -> 0
D31: TOTAL | F31: =F29+F30 -> 0
B34: Notes / Terms
B35: This quote is valid for 30 days. Pricing does not include unforeseen conditions discovered once work begins.

Sheet Invoice
B2: =CompanyName -> Your Company Name | E2: INVOICE
B3: =CompanyAddress&", "&CompanyCityStateZip -> 123 Main Street, Anytown, ST 00000
B4: =CompanyPhone&" · "&CompanyEmail -> (555) 555-5555 · you@yourcompany.com | E4: Invoice # | F4: INV-0001
E5: Date | F5: =TODAY() -> 46276
E6: Due Date | F6: =F5+14 -> 46290
B8: BILL TO
B9: Client / Company Name
B13: Item | C13: Description | D13: Qty | E13: Unit Price | F13: Line Total
B14: =IF(Quote!B14="","",Quote!B14) | C14: =IF(Quote!C14="","",Quote!C14) | D14: =IF(Quote!D14="","",Quote!D14) | E14: =IF(Quote!E14="","",Quote!E14) | F14: =IF(OR(B14="",D14=""),"",D14*E14)
B15: =IF(Quote!B15="","",Quote!B15) | C15: =IF(Quote!C15="","",Quote!C15) | D15: =IF(Quote!D15="","",Quote!D15) | E15: =IF(Quote!E15="","",Quote!E15) | F15: =IF(OR(B15="",D15=""),"",D15*E15)
B16: =IF(Quote!B16="","",Quote!B16) | C16: =IF(Quote!C16="","",Quote!C16) | D16: =IF(Quote!D16="","",Quote!D16) | E16: =IF(Quote!E16="","",Quote!E16) | F16: =IF(OR(B16="",D16=""),"",D16*E16)
B17: =IF(Quote!B17="","",Quote!B17) | C17: =IF(Quote!C17="","",Quote!C17) | D17: =IF(Quote!D17="","",Quote!D17) | E17: =IF(Quote!E17="","",Quote!E17) | F17: =IF(OR(B17="",D17=""),"",D17*E17)
B18: =IF(Quote!B18="","",Quote!B18) | C18: =IF(Quote!C18="","",Quote!C18) | D18: =IF(Quote!D18="","",Quote!D18) | E18: =IF(Quote!E18="","",Quote!E18) | F18: =IF(OR(B18="",D18=""),"",D18*E18)
B19: =IF(Quote!B19="","",Quote!B19) | C19: =IF(Quote!C19="","",Quote!C19) | D19: =IF(Quote!D19="","",Quote!D19) | E19: =IF(Quote!E19="","",Quote!E19) | F19: =IF(OR(B19="",D19=""),"",D19*E19)
B20: =IF(Quote!B20="","",Quote!B20) | C20: =IF(Quote!C20="","",Quote!C20) | D20: =IF(Quote!D20="","",Quote!D20) | E20: =IF(Quote!E20="","",Quote!E20) | F20: =IF(OR(B20="",D20=""),"",D20*E20)
B21: =IF(Quote!B21="","",Quote!B21) | C21: =IF(Quote!C21="","",Quote!C21) | D21: =IF(Quote!D21="","",Quote!D21) | E21: =IF(Quote!E21="","",Quote!E21) | F21: =IF(OR(B21="",D21=""),"",D21*E21)
B22: =IF(Quote!B22="","",Quote!B22) | C22: =IF(Quote!C22="","",Quote!C22) | D22: =IF(Quote!D22="","",Quote!D22) | E22: =IF(Quote!E22="","",Quote!E22) | F22: =IF(OR(B22="",D22=""),"",D22*E22)
B23: =IF(Quote!B23="","",Quote!B23) | C23: =IF(Quote!C23="","",Quote!C23) | D23: =IF(Quote!D23="","",Quote!D23) | E23: =IF(Quote!E23="","",Quote!E23) | F23: =IF(OR(B23="",D23=""),"",D23*E23)
B24: =IF(Quote!B24="","",Quote!B24) | C24: =IF(Quote!C24="","",Quote!C24) | D24: =IF(Quote!D24="","",Quote!D24) | E24: =IF(Quote!E24="","",Quote!E24) | F24: =IF(OR(B24="",D24=""),"",D24*E24)
B25: =IF(Quote!B25="","",Quote!B25) | C25: =IF(Quote!C25="","",Quote!C25) | D25: =IF(Quote!D25="","",Quote!D25) | E25: =IF(Quote!E25="","",Quote!E25) | F25: =IF(OR(B25="",D25=""),"",D25*E25)
... B27: =IF(Quote!B27="","",Quote!B27) | C27: =IF(Quote!C27="","",Quote!C27) | D27: =IF(Quote!D27="","",Quote!D27) | E27: =IF(Quote!E27="","",Quote!E27) | F27: =IF(OR(B27="",D27=""),"",D27*E27)
B29: Change Order Adjustments (auto-pulled from the Change Order tab)
B30: Description | F30: Cost Impact
B31: =IF('Change Order'!B14="","",'Change Order'!B14) | F31: =IF('Change Order'!D14="","",'Change Order'!D14)
B32: =IF('Change Order'!B15="","",'Change Order'!B15) | F32: =IF('Change Order'!D15="","",'Change Order'!D15)
B33: =IF('Change Order'!B16="","",'Change Order'!B16) | F33: =IF('Change Order'!D16="","",'Change Order'!D16)
B34: =IF('Change Order'!B17="","",'Change Order'!B17) | F34: =IF('Change Order'!D17="","",'Change Order'!D17)
B35: =IF('Change Order'!B18="","",'Change Order'!B18) | F35: =IF('Change Order'!D18="","",'Change Order'!D18)
B36: =IF('Change Order'!B19="","",'Change Order'!B19) | F36: =IF('Change Order'!D19="","",'Change Order'!D19)
B37: =IF('Change Order'!B20="","",'Change Order'!B20) | F37: =IF('Change Order'!D20="","",'Change Order'!D20)
B38: =IF('Change Order'!B21="","",'Change Order'!B21) | F38: =IF('Change Order'!D21="","",'Change Order'!D21)
D40: Subtotal | F40: =SUM(F14:F27,F31:F38) -> 0
D41: Tax | E41: 0 | F41: =F40*E41 -> 0
D42: TOTAL DUE | F42: =F40+F41 -> 0
B45: Notes / Terms
B46: Payment due within 14 days. Thank you for your business!

Sheet Change Order
B2: =CompanyName -> Your Company Name | D2: CHANGE ORDER
B3: =CompanyAddress&", "&CompanyCityStateZip -> 123 Main Street, Anytown, ST 00000
D4: Change Order # | E4: CO-0001
D5: Date | E5: =TODAY() -> 46276
D6: Related Job / Quote #
B8: PROJECT / CLIENT
B9: Project Name
B10: Client Name
B11: 0
B13: Description of Change | C13: Reason | D13: Cost Impact | E13: Time Impact (days)
C23: Total Cost Impact | D23: =SUM(D14:D21) -> 0
C24: Revised Contract Total | D24: =B11+D23 -> 0
B27: APPROVAL
B29: Contractor Signature | D29: Date
B31: Client Signature | D31: Date

Sheet Mileage Log
B2: MILEAGE LOG
B3: =CompanyName -> Your Company Name
F4: Period | G4: Month / Year
F5: Rate per Mile | G5: 0
B7: Date | C7: Client / Job | D7: Purpose | E7: From | F7: To | G7: Miles | H7: Reimbursement
H8: =IF(G8="","",G8*$G$5)
H9: =IF(G9="","",G9*$G$5)
H10: =IF(G10="","",G10*$G$5)
H11: =IF(G11="","",G11*$G$5)
H12: =IF(G12="","",G12*$G$5)
H13: =IF(G13="","",G13*$G$5)
H14: =IF(G14="","",G14*$G$5)
H15: =IF(G15="","",G15*$G$5)
H16: =IF(G16="","",G16*$G$5)
H17: =IF(G17="","",G17*$G$5)
H18: =IF(G18="","",G18*$G$5)
H19: =IF(G19="","",G19*$G$5)
... H27: =IF(G27="","",G27*$G$5)
F29: TOTAL | G29: =SUM(G8:G27) -> 0 | H29: =SUM(H8:H27) -> 0
B31: Set your current standard mileage rate above (check your country's tax authority for the latest rate) — every row recalculates automatically.
